{
    
     "nodes": [
 
     {
         "ID": 1,
         "input_port_length": 2,
         "output_port_length": 2,
         "input_port_width": "1",
         "output_port_width": "1",
         "register_length": 1,
         "register_width": "1",
         "code":"Local(0) = Local(0) + Input(0)*Input(1);Output(0) = Input(0);Output(1) = Input(1);printVal.printVal(Local(0))",
         "PU_type":1,
         "Data_Source_Index":"0,3"
     },
 
     {
         "ID": 2,
         "input_port_length": 2,
         "output_port_length": 2,
         "input_port_width": "1",
         "output_port_width": "1",
         "register_length": 1,
         "register_width": "1",
         "code":"Local(0) = Local(0) + Input(0)*Input(1);Output(0) = Input(0);Output(1) = Input(1);printVal.printVal(Local(0))",
         "PU_type":1,
         "Data_Source_Index":"-1,4"
     },
 
     {
         "ID": 3,
         "input_port_length": 2,
         "output_port_length": 2,
         "input_port_width": "1",
         "output_port_width": "1",
         "register_length": 1,
         "register_width": "1",
         "code":"Local(0) = Local(0) + Input(0)*Input(1);Output(0) = Input(0);Output(1) = Input(1);printVal.printVal(Local(0))",
         "PU_type":1,
         "Data_Source_Index":"-1,5"
     },

     {
        "ID": 4,
        "input_port_length": 2,
        "output_port_length": 2,
        "input_port_width": "1",
        "output_port_width": "1",
        "register_length": 1,
        "register_width": "1",
        "code":"Local(0) = Local(0) + Input(0)*Input(1);Output(0) = Input(0);Output(1) = Input(1);printVal.printVal(Local(0))",
        "PU_type":1,
        "Data_Source_Index":"1,-1"
    },

    {
        "ID": 5,
        "input_port_length": 2,
        "output_port_length": 2,
        "input_port_width": "1",
        "output_port_width": "1",
        "register_length": 1,
        "register_width": "1",
        "code":"Local(0) = Local(0) + Input(0)*Input(1);Output(0) = Input(0);Output(1) = Input(1);printVal.printVal(Local(0))",
        "PU_type":0,
        "Data_Source_Index":"-1,-1"
    },

    {
        "ID": 6,
        "input_port_length": 2,
        "output_port_length": 2,
        "input_port_width": "1",
        "output_port_width": "1",
        "register_length": 1,
        "register_width": "1",
        "code":"Local(0) = Local(0) + Input(0)*Input(1);Output(0) = Input(0);Output(1) = Input(1);printVal.printVal(Local(0))",
        "PU_type":0,
        "Data_Source_Index":"-1,-1"
    },

    {
        "ID": 7,
        "input_port_length": 2,
        "output_port_length": 2,
        "input_port_width": "1",
        "output_port_width": "1",
        "register_length": 1,
        "register_width": "1",
        "code":"Local(0) = Local(0) + Input(0)*Input(1);Output(0) = Input(0);Output(1) = Input(1);printVal.printVal(Local(0))",
        "PU_type":1,
        "Data_Source_Index":"2,-1"
    },

    {
        "ID": 8,
        "input_port_length": 2,
        "output_port_length": 2,
        "input_port_width": "1",
        "output_port_width": "1",
        "register_length": 1,
        "register_width": "1",
        "code":"Local(0) = Local(0) + Input(0)*Input(1);Output(0) = Input(0);Output(1) = Input(1);printVal.printVal(Local(0))",
        "PU_type":0,
        "Data_Source_Index":"-1,-1"
    },

    {
        "ID": 9,
        "input_port_length": 2,
        "output_port_length": 2,
        "input_port_width": "1",
        "output_port_width": "1",
        "register_length": 1,
        "register_width": "1",
        "code":"Local(0) = Local(0) + Input(0)*Input(1);Output(0) = Input(0);Output(1) = Input(1);printVal.printVal(Local(0)); if(!Output(1).isInstanceOf[NaN]) exit()",
        "PU_type":-1,
        "Data_Source_Index":"-1,-1"
    }

    ]
 
   }